<?xml version="1.0"?>
<!DOCTYPE hibernate-mapping PUBLIC "-//Hibernate/Hibernate Mapping DTD 3.0//EN"
"http://hibernate.sourceforge.net/hibernate-mapping-3.0.dtd">
<!-- Generated Mar 2, 2015 3:36:22 PM by Hibernate Tools 3.4.0.CR1 -->
<hibernate-mapping>
    <class name="com.nsmjsf.web.datamodels.ForumThread" table="forum_thread" catalog="admin_nsmjsf">
        <id name="forumThreadId" type="java.lang.Integer">
            <column name="forum_thread_id" />
            <generator class="identity" />
        </id>
        <many-to-one name="post" class="com.nsmjsf.web.datamodels.Post" fetch="select">
            <column name="forum_thread_post_id" not-null="true" />
        </many-to-one>
    </class>
</hibernate-mapping>
